apex_client/__init__.py
apex_client/objects/__init__.py
apex_client/objects/apex_object.py
apex_client/objects/exceptions.py
apex_client/objects/events/__init__.py
apex_client/objects/events/area.py
apex_client/objects/events/day.py
apex_client/objects/events/event.py
apex_client/objects/events/event_area.py
apex_client/objects/events/event_participant.py
apex_client/objects/events/mail_template.py
apex_client/objects/events/session.py
apex_client/objects/events/session_participant.py
apex_client/objects/events/type.py
apex_client/objects/events/mixins/__init__.py
apex_client/objects/events/mixins/event_participant_mixin.py
apex_client/objects/invoices/__init__.py
apex_client/objects/invoices/currency.py
apex_client/objects/invoices/invoice.py
apex_client/objects/invoices/invoice_row.py
apex_client/objects/invoices/price.py
apex_client/objects/participants/__init__.py
apex_client/objects/participants/address.py
apex_client/objects/participants/company.py
apex_client/objects/participants/network.py
apex_client/objects/participants/participant.py
apex_client/objects/portals/__init__.py
apex_client/objects/portals/portal.py
apex_client/objects/portals/portal_event.py
apex_client/request/__init__.py
apex_client/request/apex_request.py
apex_client-0.1.3.dist-info/LICENSE
apex_client-0.1.3.dist-info/METADATA
apex_client-0.1.3.dist-info/WHEEL
apex_client-0.1.3.dist-info/top_level.txt
apex_client-0.1.3.dist-info/RECORD
