Metadata-Version: 2.1
Name: apex-client
Version: 0.1.3
Summary: UNKNOWN
Home-page: https://github.com/promoteinternational/apex-ng-client
Author: Andréas Kühne
Author-email: andreas.kuhne@promoteint.com
License: UNKNOWN
Platform: UNKNOWN
Classifier: Programming Language :: Python :: 3
Classifier: License :: OSI Approved :: MIT License
Classifier: Operating System :: OS Independent
Requires-Dist: apex-auth (>=0.2.2)
Requires-Dist: django (>=2.2.2)
Requires-Dist: python-dateutil (>=2.8.0)
Requires-Dist: requests (>=2.22.0)
